{
  "$schema": "https://ui.shadcn.com/schema/registry-item.json",
  "name": "card-with-background-images-demo",
  "type": "registry:example",
  "registryDependencies": [
    "card"
  ],
  "files": [
    {
      "path": "src/registry/pure-ui/examples/card/card-with-background-images-demo.tsx",
      "content": "import { ArrowUpRight } from \"lucide-react\";\r\n\r\nimport { Card, CardHeader } from \"@/registry/pure-ui/ui/card\";\r\nimport { Button } from \"@/registry/pure-ui/ui/button\";\r\n\r\nexport function CardWithBackgroundImagesDemo() {\r\n  return (\r\n    <div className=\"flex flex-col gap-6 md:flex-row\">\r\n      <Card className=\"w-[320px] aspect-square before:absolute before:left-0 before:right-0 before:top-0 before:h-[44px] before:bg-linear-to-b before:from-black/80 before:to-transparent before:z-10\">\r\n        <img\r\n          alt=\"Beautiful aerial view of Buenos Aires cityscape\"\r\n          aria-hidden=\"true\"\r\n          className=\"pointer-events-none absolute inset-0 h-full w-full select-none object-cover\"\r\n          src=\"https://pbs.twimg.com/media/G2gchvnWoAAvkGG?format=jpg&name=large\"\r\n        />\r\n        <CardHeader className=\"z-10 flex flex-row items-center justify-between w-full\">\r\n          <div>\r\n            <div className=\"text-sm font-medium text-white\">Naruto</div>\r\n            <div className=\"text-xs text-white/60\">Shonen</div>\r\n          </div>\r\n          <Button\r\n            aria-label=\"View Buenos Aires on map\"\r\n            size=\"sm\"\r\n            variant=\"link\"\r\n            className=\"text-white\"\r\n          >\r\n            Season 2\r\n            <ArrowUpRight className=\"size-4 ml-2\" />\r\n          </Button>\r\n        </CardHeader>\r\n      </Card>\r\n    </div>\r\n  );\r\n}\r\n",
      "type": "registry:example"
    }
  ]
}